<?xml version="1.0" encoding="windows-1252" ?>
<!DOCTYPE Entity SYSTEM "jbo_03_01.dtd">
<!---->
<Entity
  xmlns="http://xmlns.oracle.com/bc4j"
  Name="XxscPayApplLinesEO"
  Version="11.1.1.66.73"
  InheritPersonalization="merge"
  DBObjectType="table"
  DBObjectName="XXSC_PAY_APPL_LINES"
  AliasName="XxscPayApplLinesEO"
  BindingStyle="OracleName"
  UseGlueCode="false">
  <DesignTime>
    <Attr Name="_codeGenFlag2" Value="Access"/>
    <AttrArray Name="_publishEvents"/>
  </DesignTime>
  <Attribute
    Name="ApplLineId"
    IsUpdateable="while_insert"
    IsNotNull="true"
    ColumnName="APPL_LINE_ID"
    SQLType="NUMERIC"
    Type="oracle.jbo.domain.Number"
    ColumnType="NUMBER"
    TableName="XXSC_PAY_APPL_LINES"
    PrimaryKey="true">
    <DesignTime>
      <Attr Name="_DisplaySize" Value="39"/>
    </DesignTime>
    <TransientExpression><![CDATA[(new oracle.jbo.server.SequenceImpl("XXSC_APPL_LINE_ID_S",adf.object.getDBTransaction())).getSequenceNumber()]]></TransientExpression>
  </Attribute>
  <Attribute
    Name="ApplHeaderId"
    IsNotNull="true"
    ColumnName="APPL_HEADER_ID"
    SQLType="NUMERIC"
    Type="oracle.jbo.domain.Number"
    ColumnType="NUMBER"
    TableName="XXSC_PAY_APPL_LINES">
    <DesignTime>
      <Attr Name="_DisplaySize" Value="39"/>
    </DesignTime>
  </Attribute>
  <Attribute
    Name="DataSetId"
    ColumnName="DATA_SET_ID"
    SQLType="NUMERIC"
    Type="oracle.jbo.domain.Number"
    ColumnType="NUMBER"
    TableName="XXSC_PAY_APPL_LINES">
    <DesignTime>
      <Attr Name="_DisplaySize" Value="39"/>
    </DesignTime>
  </Attribute>
  <Attribute
    Name="ContHeaderId"
    ColumnName="CONT_HEADER_ID"
    SQLType="NUMERIC"
    Type="oracle.jbo.domain.Number"
    ColumnType="NUMBER"
    TableName="XXSC_PAY_APPL_LINES">
    <DesignTime>
      <Attr Name="_DisplaySize" Value="39"/>
    </DesignTime>
  </Attribute>
  <Attribute
    Name="ContLineId"
    IsNotNull="true"
    ColumnName="CONT_LINE_ID"
    SQLType="NUMERIC"
    Type="oracle.jbo.domain.Number"
    ColumnType="NUMBER"
    TableName="XXSC_PAY_APPL_LINES">
    <DesignTime>
      <Attr Name="_DisplaySize" Value="39"/>
    </DesignTime>
  </Attribute>
  <Attribute
    Name="Version"
    IsNotNull="true"
    ColumnName="VERSION"
    SQLType="NUMERIC"
    Type="oracle.jbo.domain.Number"
    ColumnType="NUMBER"
    TableName="XXSC_PAY_APPL_LINES">
    <DesignTime>
      <Attr Name="_DisplaySize" Value="39"/>
    </DesignTime>
  </Attribute>
  <Attribute
    Name="PrevPerc"
    ColumnName="PREV_PERC"
    SQLType="NUMERIC"
    Type="oracle.jbo.domain.Number"
    ColumnType="NUMBER"
    TableName="XXSC_PAY_APPL_LINES">
    <DesignTime>
      <Attr Name="_DisplaySize" Value="39"/>
    </DesignTime>
  </Attribute>
  <Attribute
    Name="PrevSupOnlyQty"
    ColumnName="PREV_SUP_ONLY_QTY"
    SQLType="NUMERIC"
    Type="oracle.jbo.domain.Number"
    ColumnType="NUMBER"
    TableName="XXSC_PAY_APPL_LINES">
    <DesignTime>
      <Attr Name="_DisplaySize" Value="39"/>
    </DesignTime>
  </Attribute>
  <Attribute
    Name="PrevSupInsQty"
    ColumnName="PREV_SUP_INS_QTY"
    SQLType="NUMERIC"
    Type="oracle.jbo.domain.Number"
    ColumnType="NUMBER"
    TableName="XXSC_PAY_APPL_LINES">
    <DesignTime>
      <Attr Name="_DisplaySize" Value="39"/>
    </DesignTime>
  </Attribute>
  <Attribute
    Name="PrevTotQty"
    ColumnName="PREV_TOT_QTY"
    SQLType="NUMERIC"
    Type="oracle.jbo.domain.Number"
    ColumnType="NUMBER"
    TableName="XXSC_PAY_APPL_LINES">
    <DesignTime>
      <Attr Name="_DisplaySize" Value="39"/>
    </DesignTime>
  </Attribute>
  <Attribute
    Name="PrevAmount"
    ColumnName="PREV_AMOUNT"
    SQLType="NUMERIC"
    Type="oracle.jbo.domain.Number"
    ColumnType="NUMBER"
    TableName="XXSC_PAY_APPL_LINES">
    <DesignTime>
      <Attr Name="_DisplaySize" Value="39"/>
    </DesignTime>
  </Attribute>
  <Attribute
    Name="CurrPerc"
    ColumnName="CURR_PERC"
    SQLType="NUMERIC"
    Type="oracle.jbo.domain.Number"
    ColumnType="NUMBER"
    TableName="XXSC_PAY_APPL_LINES">
    <DesignTime>
      <Attr Name="_DisplaySize" Value="39"/>
    </DesignTime>
  </Attribute>
  <Attribute
    Name="CurrSupOnlyQty"
    ColumnName="CURR_SUP_ONLY_QTY"
    SQLType="NUMERIC"
    Type="oracle.jbo.domain.Number"
    ColumnType="NUMBER"
    TableName="XXSC_PAY_APPL_LINES">
    <DesignTime>
      <Attr Name="_DisplaySize" Value="39"/>
    </DesignTime>
  </Attribute>
  <Attribute
    Name="CurrSupInsQty"
    ColumnName="CURR_SUP_INS_QTY"
    SQLType="NUMERIC"
    Type="oracle.jbo.domain.Number"
    ColumnType="NUMBER"
    TableName="XXSC_PAY_APPL_LINES">
    <DesignTime>
      <Attr Name="_DisplaySize" Value="39"/>
    </DesignTime>
  </Attribute>
  <Attribute
    Name="CurrTotQty"
    ColumnName="CURR_TOT_QTY"
    SQLType="NUMERIC"
    Type="oracle.jbo.domain.Number"
    ColumnType="NUMBER"
    TableName="XXSC_PAY_APPL_LINES">
    <DesignTime>
      <Attr Name="_DisplaySize" Value="39"/>
    </DesignTime>
  </Attribute>
  <Attribute
    Name="CurrAmount"
    ColumnName="CURR_AMOUNT"
    SQLType="NUMERIC"
    Type="oracle.jbo.domain.Number"
    ColumnType="NUMBER"
    TableName="XXSC_PAY_APPL_LINES">
    <DesignTime>
      <Attr Name="_DisplaySize" Value="39"/>
    </DesignTime>
  </Attribute>
  <Attribute
    Name="CumPerc"
    ColumnName="CUM_PERC"
    SQLType="NUMERIC"
    Type="oracle.jbo.domain.Number"
    ColumnType="NUMBER"
    TableName="XXSC_PAY_APPL_LINES">
    <DesignTime>
      <Attr Name="_DisplaySize" Value="39"/>
    </DesignTime>
  </Attribute>
  <Attribute
    Name="CumSupOnlyQty"
    ColumnName="CUM_SUP_ONLY_QTY"
    SQLType="NUMERIC"
    Type="oracle.jbo.domain.Number"
    ColumnType="NUMBER"
    TableName="XXSC_PAY_APPL_LINES">
    <DesignTime>
      <Attr Name="_DisplaySize" Value="39"/>
    </DesignTime>
  </Attribute>
  <Attribute
    Name="CumSupInsQty"
    ColumnName="CUM_SUP_INS_QTY"
    SQLType="NUMERIC"
    Type="oracle.jbo.domain.Number"
    ColumnType="NUMBER"
    TableName="XXSC_PAY_APPL_LINES">
    <DesignTime>
      <Attr Name="_DisplaySize" Value="39"/>
    </DesignTime>
  </Attribute>
  <Attribute
    Name="CumTotQty"
    ColumnName="CUM_TOT_QTY"
    SQLType="NUMERIC"
    Type="oracle.jbo.domain.Number"
    ColumnType="NUMBER"
    TableName="XXSC_PAY_APPL_LINES">
    <DesignTime>
      <Attr Name="_DisplaySize" Value="39"/>
    </DesignTime>
  </Attribute>
  <Attribute
    Name="CumAmount"
    ColumnName="CUM_AMOUNT"
    SQLType="NUMERIC"
    Type="oracle.jbo.domain.Number"
    ColumnType="NUMBER"
    TableName="XXSC_PAY_APPL_LINES">
    <DesignTime>
      <Attr Name="_DisplaySize" Value="39"/>
    </DesignTime>
  </Attribute>
  <Attribute
    Name="Remarks"
    Precision="2000"
    ColumnName="REMARKS"
    SQLType="VARCHAR"
    Type="java.lang.String"
    ColumnType="VARCHAR2"
    TableName="XXSC_PAY_APPL_LINES">
    <DesignTime>
      <Attr Name="_DisplaySize" Value="2000"/>
    </DesignTime>
  </Attribute>
  <Attribute
    Name="OrgId"
    ColumnName="ORG_ID"
    SQLType="NUMERIC"
    Type="oracle.jbo.domain.Number"
    ColumnType="NUMBER"
    TableName="XXSC_PAY_APPL_LINES">
    <DesignTime>
      <Attr Name="_DisplaySize" Value="39"/>
    </DesignTime>
  </Attribute>
  <Attribute
    Name="ObjectVersionNumber"
    ColumnName="OBJECT_VERSION_NUMBER"
    SQLType="NUMERIC"
    Type="oracle.jbo.domain.Number"
    ColumnType="NUMBER"
    TableName="XXSC_PAY_APPL_LINES">
    <DesignTime>
      <Attr Name="_DisplaySize" Value="39"/>
    </DesignTime>
  </Attribute>
  <Attribute
    Name="AttributeCategory"
    Precision="240"
    ColumnName="ATTRIBUTE_CATEGORY"
    SQLType="VARCHAR"
    Type="java.lang.String"
    ColumnType="VARCHAR2"
    TableName="XXSC_PAY_APPL_LINES">
    <DesignTime>
      <Attr Name="_DisplaySize" Value="240"/>
    </DesignTime>
  </Attribute>
  <Attribute
    Name="Attribute1"
    Precision="240"
    ColumnName="ATTRIBUTE1"
    SQLType="VARCHAR"
    Type="java.lang.String"
    ColumnType="VARCHAR2"
    TableName="XXSC_PAY_APPL_LINES">
    <DesignTime>
      <Attr Name="_DisplaySize" Value="240"/>
    </DesignTime>
  </Attribute>
  <Attribute
    Name="Attribute2"
    Precision="240"
    ColumnName="ATTRIBUTE2"
    SQLType="VARCHAR"
    Type="java.lang.String"
    ColumnType="VARCHAR2"
    TableName="XXSC_PAY_APPL_LINES">
    <DesignTime>
      <Attr Name="_DisplaySize" Value="240"/>
    </DesignTime>
  </Attribute>
  <Attribute
    Name="Attribute3"
    Precision="240"
    ColumnName="ATTRIBUTE3"
    SQLType="VARCHAR"
    Type="java.lang.String"
    ColumnType="VARCHAR2"
    TableName="XXSC_PAY_APPL_LINES">
    <DesignTime>
      <Attr Name="_DisplaySize" Value="240"/>
    </DesignTime>
  </Attribute>
  <Attribute
    Name="Attribute4"
    Precision="240"
    ColumnName="ATTRIBUTE4"
    SQLType="VARCHAR"
    Type="java.lang.String"
    ColumnType="VARCHAR2"
    TableName="XXSC_PAY_APPL_LINES">
    <DesignTime>
      <Attr Name="_DisplaySize" Value="240"/>
    </DesignTime>
  </Attribute>
  <Attribute
    Name="Attribute5"
    Precision="240"
    ColumnName="ATTRIBUTE5"
    SQLType="VARCHAR"
    Type="java.lang.String"
    ColumnType="VARCHAR2"
    TableName="XXSC_PAY_APPL_LINES">
    <DesignTime>
      <Attr Name="_DisplaySize" Value="240"/>
    </DesignTime>
  </Attribute>
  <Attribute
    Name="Attribute6"
    Precision="240"
    ColumnName="ATTRIBUTE6"
    SQLType="VARCHAR"
    Type="java.lang.String"
    ColumnType="VARCHAR2"
    TableName="XXSC_PAY_APPL_LINES">
    <DesignTime>
      <Attr Name="_DisplaySize" Value="240"/>
    </DesignTime>
  </Attribute>
  <Attribute
    Name="Attribute7"
    Precision="240"
    ColumnName="ATTRIBUTE7"
    SQLType="VARCHAR"
    Type="java.lang.String"
    ColumnType="VARCHAR2"
    TableName="XXSC_PAY_APPL_LINES">
    <DesignTime>
      <Attr Name="_DisplaySize" Value="240"/>
    </DesignTime>
  </Attribute>
  <Attribute
    Name="Attribute8"
    Precision="240"
    ColumnName="ATTRIBUTE8"
    SQLType="VARCHAR"
    Type="java.lang.String"
    ColumnType="VARCHAR2"
    TableName="XXSC_PAY_APPL_LINES">
    <DesignTime>
      <Attr Name="_DisplaySize" Value="240"/>
    </DesignTime>
  </Attribute>
  <Attribute
    Name="Attribute9"
    Precision="240"
    ColumnName="ATTRIBUTE9"
    SQLType="VARCHAR"
    Type="java.lang.String"
    ColumnType="VARCHAR2"
    TableName="XXSC_PAY_APPL_LINES">
    <DesignTime>
      <Attr Name="_DisplaySize" Value="240"/>
    </DesignTime>
  </Attribute>
  <Attribute
    Name="Attribute10"
    Precision="240"
    ColumnName="ATTRIBUTE10"
    SQLType="VARCHAR"
    Type="java.lang.String"
    ColumnType="VARCHAR2"
    TableName="XXSC_PAY_APPL_LINES">
    <DesignTime>
      <Attr Name="_DisplaySize" Value="240"/>
    </DesignTime>
  </Attribute>
  <Attribute
    Name="CreatedBy"
    IsUpdateable="while_insert"
    IsNotNull="true"
    Precision="64"
    ColumnName="CREATED_BY"
    SQLType="VARCHAR"
    Type="java.lang.String"
    ColumnType="VARCHAR2"
    TableName="XXSC_PAY_APPL_LINES"
    HistoryColumn="UserHistory">
    <DesignTime>
      <Attr Name="_DisplaySize" Value="64"/>
    </DesignTime>
  </Attribute>
  <Attribute
    Name="CreationDate"
    IsUpdateable="while_insert"
    IsNotNull="true"
    ColumnName="CREATION_DATE"
    SQLType="TIMESTAMP"
    Type="oracle.jbo.domain.Timestamp"
    ColumnType="TIMESTAMP"
    TableName="XXSC_PAY_APPL_LINES"
    HistoryColumn="DateHistory">
    <DesignTime>
      <Attr Name="_DisplaySize" Value="11"/>
    </DesignTime>
  </Attribute>
  <Attribute
    Name="LastUpdatedBy"
    IsNotNull="true"
    Precision="64"
    ColumnName="LAST_UPDATED_BY"
    SQLType="VARCHAR"
    Type="java.lang.String"
    ColumnType="VARCHAR2"
    TableName="XXSC_PAY_APPL_LINES"
    HistoryColumn="UserHistory">
    <DesignTime>
      <Attr Name="_DisplaySize" Value="64"/>
    </DesignTime>
  </Attribute>
  <Attribute
    Name="LastUpdateDate"
    IsNotNull="true"
    ColumnName="LAST_UPDATE_DATE"
    SQLType="TIMESTAMP"
    Type="oracle.jbo.domain.Timestamp"
    ColumnType="TIMESTAMP"
    TableName="XXSC_PAY_APPL_LINES"
    HistoryColumn="DateHistory">
    <DesignTime>
      <Attr Name="_DisplaySize" Value="11"/>
    </DesignTime>
  </Attribute>
  <Attribute
    Name="LastUpdateLogin"
    Precision="32"
    ColumnName="LAST_UPDATE_LOGIN"
    SQLType="VARCHAR"
    Type="java.lang.String"
    ColumnType="VARCHAR2"
    TableName="XXSC_PAY_APPL_LINES"
    HistoryColumn="UserHistory">
    <DesignTime>
      <Attr Name="_DisplaySize" Value="32"/>
    </DesignTime>
  </Attribute>
  <AccessorAttribute
    Name="XxscPayApplHeadersEO"
    Association="Assoc.PayApplLineHdrFkAssoc"
    AssociationEnd="Assoc.PayApplLineHdrFkAssoc.XxscPayApplHeadersEO"
    AssociationOtherEnd="Assoc.PayApplLineHdrFkAssoc.XxscPayApplLinesEO"
    Type="oracle.jbo.server.EntityImpl"
    IsUpdateable="true"/>
  <Key
    Name="SysC0025506">
    <DesignTime>
      <Attr Name="_DBObjectName" Value="SYS_C0025506"/>
      <Attr Name="_checkCondition" Value='"APPL_LINE_ID" IS NOT NULL'/>
      <Attr Name="_isCheck" Value="true"/>
    </DesignTime>
    <AttrArray Name="Attributes">
      <Item Value="entity.XxscPayApplLinesEO.ApplLineId"/>
    </AttrArray>
  </Key>
  <Key
    Name="SysC0025507">
    <DesignTime>
      <Attr Name="_DBObjectName" Value="SYS_C0025507"/>
      <Attr Name="_checkCondition" Value='"APPL_HEADER_ID" IS NOT NULL'/>
      <Attr Name="_isCheck" Value="true"/>
    </DesignTime>
    <AttrArray Name="Attributes">
      <Item Value="entity.XxscPayApplLinesEO.ApplHeaderId"/>
    </AttrArray>
  </Key>
  <Key
    Name="SysC0025508">
    <DesignTime>
      <Attr Name="_DBObjectName" Value="SYS_C0025508"/>
      <Attr Name="_checkCondition" Value='"CONT_LINE_ID" IS NOT NULL'/>
      <Attr Name="_isCheck" Value="true"/>
    </DesignTime>
    <AttrArray Name="Attributes">
      <Item Value="entity.XxscPayApplLinesEO.ContLineId"/>
    </AttrArray>
  </Key>
  <Key
    Name="SysC0025509">
    <DesignTime>
      <Attr Name="_DBObjectName" Value="SYS_C0025509"/>
      <Attr Name="_checkCondition" Value='"VERSION" IS NOT NULL'/>
      <Attr Name="_isCheck" Value="true"/>
    </DesignTime>
    <AttrArray Name="Attributes">
      <Item Value="entity.XxscPayApplLinesEO.Version"/>
    </AttrArray>
  </Key>
  <Key
    Name="SysC0025510">
    <DesignTime>
      <Attr Name="_DBObjectName" Value="SYS_C0025510"/>
      <Attr Name="_checkCondition" Value='"CREATED_BY" IS NOT NULL'/>
      <Attr Name="_isCheck" Value="true"/>
    </DesignTime>
    <AttrArray Name="Attributes">
      <Item Value="entity.XxscPayApplLinesEO.CreatedBy"/>
    </AttrArray>
  </Key>
  <Key
    Name="SysC0025511">
    <DesignTime>
      <Attr Name="_DBObjectName" Value="SYS_C0025511"/>
      <Attr Name="_checkCondition" Value='"CREATION_DATE" IS NOT NULL'/>
      <Attr Name="_isCheck" Value="true"/>
    </DesignTime>
    <AttrArray Name="Attributes">
      <Item Value="entity.XxscPayApplLinesEO.CreationDate"/>
    </AttrArray>
  </Key>
  <Key
    Name="SysC0025512">
    <DesignTime>
      <Attr Name="_DBObjectName" Value="SYS_C0025512"/>
      <Attr Name="_checkCondition" Value='"LAST_UPDATED_BY" IS NOT NULL'/>
      <Attr Name="_isCheck" Value="true"/>
    </DesignTime>
    <AttrArray Name="Attributes">
      <Item Value="entity.XxscPayApplLinesEO.LastUpdatedBy"/>
    </AttrArray>
  </Key>
  <Key
    Name="SysC0025513">
    <DesignTime>
      <Attr Name="_DBObjectName" Value="SYS_C0025513"/>
      <Attr Name="_checkCondition" Value='"LAST_UPDATE_DATE" IS NOT NULL'/>
      <Attr Name="_isCheck" Value="true"/>
    </DesignTime>
    <AttrArray Name="Attributes">
      <Item Value="entity.XxscPayApplLinesEO.LastUpdateDate"/>
    </AttrArray>
  </Key>
  <Key
    Name="XxscPayApplLinesPk"
    PrimaryKey="true">
    <DesignTime>
      <Attr Name="_DBObjectName" Value="XXSC_PAY_APPL_LINES_PK"/>
    </DesignTime>
    <AttrArray Name="Attributes">
      <Item Value="entity.XxscPayApplLinesEO.ApplLineId"/>
    </AttrArray>
  </Key>
  <Key
    Name="PayApplLineHdrFk">
    <DesignTime>
      <Attr Name="_referencedKey" Value="XXSC_PAY_APPL_HEADERS_PK"/>
      <Attr Name="_isForeign" Value="true"/>
      <Attr Name="_DBObjectName" Value="PAY_APPL_LINE_HDR_FK"/>
    </DesignTime>
    <AttrArray Name="Attributes">
      <Item Value="entity.XxscPayApplLinesEO.ApplHeaderId"/>
    </AttrArray>
  </Key>
</Entity>
